{
  "time_posted": 1652289193,
  "next_scheduled_post_time": 1652289253,
  "leaderboard": [
    {
      "name": "棋怪.科研子",
      "rank": 1,
      "level_score": 18345
    },
    {
      "name": "★★★ Chính Mập ★★★",
      "rank": 2,
      "level_score": 18262
    },
    {
      "name": "PoutyPanda🐼",
      "rank": 3,
      "level_score": 18150
    },
    {
      "name": "Dr.Doom",
      "rank": 4,
      "level_score": 18144
    },
    {
      "name": "wuhek",
      "rank": 5,
      "level_score": 18076
    },
    {
      "name": "PoutyPanda🐼",
      "rank": 6,
      "level_score": 18042
    },
    {
      "name": "[DUVN]lqloc1710",
      "rank": 7,
      "level_score": 17973
    },
    {
      "name": "Nắm Đôi Bàn Tay",
      "rank": 8,
      "level_score": 17930
    },
    {
      "name": "Dr.Omni",
      "rank": 9,
      "level_score": 17829
    },
    {
      "name": "不冷灬",
      "rank": 10,
      "level_score": 17811
    },
    {
      "name": "[DUVN].DeadGame",
      "rank": 11,
      "level_score": 17784
    },
    {
      "name": "Alvin",
      "rank": 12,
      "level_score": 17673
    },
    {
      "name": "hc\"VARYAG\"",
      "rank": 13,
      "level_score": 17657
    },
    {
      "name": "夜枫流萤灬",
      "rank": 14,
      "level_score": 17631
    },
    {
      "name": "Zomb!e😎",
      "rank": 15,
      "level_score": 17601
    },
    {
      "name": "Максюшка",
      "rank": 16,
      "level_score": 17508
    },
    {
      "name": "心安即归处",
      "rank": 17,
      "level_score": 17435
    },
    {
      "name": "JP",
      "rank": 18,
      "level_score": 17411
    },
    {
      "name": "AusOne-刺客王",
      "rank": 19,
      "level_score": 17404
    },
    {
      "name": "Putin_Die_Pls 🔥",
      "rank": 20,
      "level_score": 17396
    },
    {
      "name": "-",
      "rank": 21,
      "level_score": 17381
    },
    {
      "name": "SHAULINx",
      "rank": 22,
      "level_score": 17369
    },
    {
      "name": "Celtos",
      "rank": 23,
      "level_score": 17365
    },
    {
      "name": "Dani",
      "rank": 24,
      "level_score": 17361
    },
    {
      "name": "String",
      "rank": 25,
      "level_score": 17346
    },
    {
      "name": "【MUGA】Niemand",
      "rank": 26,
      "level_score": 17329
    },
    {
      "name": "JPeG",
      "rank": 27,
      "level_score": 17323
    },
    {
      "name": "kilroy",
      "rank": 28,
      "level_score": 17322
    },
    {
      "name": "300IQ",
      "rank": 29,
      "level_score": 17314
    },
    {
      "name": "[DUVN].Roihoidichoi",
      "rank": 30,
      "level_score": 17264
    },
    {
      "name": "fly",
      "rank": 31,
      "level_score": 17242
    },
    {
      "name": "Pabluchisss",
      "rank": 32,
      "level_score": 17220
    },
    {
      "name": "[DUVN].Eydee",
      "rank": 33,
      "level_score": 17212
    },
    {
      "name": "HEFFDAWGZ",
      "rank": 34,
      "level_score": 17192
    },
    {
      "name": "BUGIMAN",
      "rank": 35,
      "level_score": 17130
    },
    {
      "name": "Drenzium",
      "rank": 36,
      "level_score": 17060
    },
    {
      "name": "Raiz",
      "rank": 37,
      "level_score": 17053
    },
    {
      "name": "[DUVN] BeeIzMe",
      "rank": 38,
      "level_score": 17037
    },
    {
      "name": "[DUVN].RubickLinh",
      "rank": 39,
      "level_score": 17035
    },
    {
      "name": "相逢何必曾相识",
      "rank": 40,
      "level_score": 17007
    },
    {
      "name": "foster🌼",
      "rank": 41,
      "level_score": 16985
    },
    {
      "name": "Techies",
      "rank": 42,
      "level_score": 16978
    },
    {
      "name": "SephiHorse",
      "rank": 43,
      "level_score": 16975
    },
    {
      "name": "Whatdafaq",
      "rank": 44,
      "level_score": 16935
    },
    {
      "name": "Jerovich",
      "rank": 45,
      "level_score": 16932
    },
    {
      "name": "Feiz",
      "rank": 46,
      "level_score": 16904
    },
    {
      "name": "che suka",
      "rank": 47,
      "level_score": 16850
    },
    {
      "name": "play | вася",
      "rank": 48,
      "level_score": 16849
    },
    {
      "name": "dcb",
      "rank": 49,
      "level_score": 16832
    },
    {
      "name": "Aung Pyae",
      "rank": 50,
      "level_score": 16829
    },
    {
      "name": "♍ Быстрый артист ",
      "rank": 51,
      "level_score": 16813
    },
    {
      "name": "Oiwoy",
      "rank": 52,
      "level_score": 16808
    },
    {
      "name": "TheHornOfMagnus",
      "rank": 53,
      "level_score": 16805
    },
    {
      "name": "silveryoung",
      "rank": 54,
      "level_score": 16803
    },
    {
      "name": "伊藤誠",
      "rank": 55,
      "level_score": 16792
    },
    {
      "name": "Zy13",
      "rank": 56,
      "level_score": 16775
    },
    {
      "name": "C Cloud",
      "rank": 57,
      "level_score": 16770
    },
    {
      "name": "天凉好个秋",
      "rank": 58,
      "level_score": 16759
    },
    {
      "name": "纯良八度",
      "rank": 59,
      "level_score": 16752
    },
    {
      "name": "tester",
      "rank": 60,
      "level_score": 16747
    },
    {
      "name": "Christ`j™",
      "rank": 61,
      "level_score": 16742
    },
    {
      "name": "Атака Хуем",
      "rank": 62,
      "level_score": 16739
    },
    {
      "name": "William Powers",
      "rank": 63,
      "level_score": 16718
    },
    {
      "name": "Zanfyste",
      "rank": 64,
      "level_score": 16715
    },
    {
      "name": "BirdyLord",
      "rank": 65,
      "level_score": 16699
    },
    {
      "name": "fky0712",
      "rank": 66,
      "level_score": 16658
    },
    {
      "name": "Arslan",
      "rank": 67,
      "level_score": 16638
    },
    {
      "name": "Graham's number",
      "rank": 68,
      "level_score": 16633
    },
    {
      "name": "Zєяoιиccuвuѕ★",
      "rank": 69,
      "level_score": 16622
    },
    {
      "name": "大方",
      "rank": 70,
      "level_score": 16612
    },
    {
      "name": "Megwoo",
      "rank": 71,
      "level_score": 16611
    },
    {
      "name": "Woof",
      "rank": 72,
      "level_score": 16604
    },
    {
      "name": "Lagoon",
      "rank": 73,
      "level_score": 16595
    },
    {
      "name": "喊牙牙",
      "rank": 74,
      "level_score": 16591
    },
    {
      "name": "いち",
      "rank": 75,
      "level_score": 16579
    },
    {
      "name": "和成天下",
      "rank": 76,
      "level_score": 16568
    },
    {
      "name": "JunioR",
      "rank": 77,
      "level_score": 16565
    },
    {
      "name": "Who ill, ah?",
      "rank": 78,
      "level_score": 16545
    },
    {
      "name": "caPu",
      "rank": 79,
      "level_score": 16530
    },
    {
      "name": "Enigma AOHP",
      "rank": 80,
      "level_score": 16526
    },
    {
      "name": "Wannabe-N0tail",
      "rank": 81,
      "level_score": 16511
    },
    {
      "name": "凯丶577",
      "rank": 82,
      "level_score": 16504
    },
    {
      "name": "burka888",
      "rank": 83,
      "level_score": 16502
    },
    {
      "name": "瓤析",
      "rank": 84,
      "level_score": 16491
    },
    {
      "name": "Astrophytum",
      "rank": 85,
      "level_score": 16450
    },
    {
      "name": "Rexy",
      "rank": 86,
      "level_score": 16447
    },
    {
      "name": "sweetfatty",
      "rank": 87,
      "level_score": 16438
    },
    {
      "name": "supertyr",
      "rank": 88,
      "level_score": 16437
    },
    {
      "name": "Focus",
      "rank": 89,
      "level_score": 16429
    },
    {
      "name": "ArchieEbuchiBrakonier",
      "rank": 90,
      "level_score": 16428
    },
    {
      "name": "dzuga",
      "rank": 91,
      "level_score": 16378
    },
    {
      "name": "barsa-seclub",
      "rank": 92,
      "level_score": 16356
    },
    {
      "name": "76561199105316378",
      "rank": 93,
      "level_score": 16347
    },
    {
      "name": "Человекчебурек",
      "rank": 94,
      "level_score": 16341
    },
    {
      "name": "502 bad gateway",
      "rank": 95,
      "level_score": 16322
    },
    {
      "name": "Daibert",
      "rank": 96,
      "level_score": 16319
    },
    {
      "name": "Nickps (Peruvian Jitch)",
      "rank": 97,
      "level_score": 16317
    },
    {
      "name": "PoomPradu",
      "rank": 98,
      "level_score": 16309
    },
    {
      "name": "Lightway(indopride)",
      "rank": 99,
      "level_score": 16300
    },
    {
      "name": "巴啦啦老魔仙",
      "rank": 100,
      "level_score": 16294
    },
    {
      "name": "milanology",
      "rank": 101,
      "level_score": 16282
    },
    {
      "name": "心态帝",
      "rank": 102,
      "level_score": 16282
    },
    {
      "name": "🦄Fantastiс",
      "rank": 103,
      "level_score": 16266
    },
    {
      "name": "嗷卵犟",
      "rank": 104,
      "level_score": 16241
    },
    {
      "name": "_NSTR_",
      "rank": 105,
      "level_score": 16233
    },
    {
      "name": "mynameisbest*",
      "rank": 106,
      "level_score": 16230
    },
    {
      "name": "我摊牌了",
      "rank": 107,
      "level_score": 16225
    },
    {
      "name": "Zamaka",
      "rank": 108,
      "level_score": 16221
    },
    {
      "name": "25717755",
      "rank": 109,
      "level_score": 16219
    },
    {
      "name": "garden83",
      "rank": 110,
      "level_score": 16210
    },
    {
      "name": "Magnum",
      "rank": 111,
      "level_score": 16207
    },
    {
      "name": "肖恩",
      "rank": 112,
      "level_score": 16205
    },
    {
      "name": "412775197",
      "rank": 113,
      "level_score": 16204
    },
    {
      "name": "FRANT",
      "rank": 114,
      "level_score": 16191
    },
    {
      "name": "Ojaaan",
      "rank": 115,
      "level_score": 16177
    },
    {
      "name": "Hello\"",
      "rank": 116,
      "level_score": 16176
    },
    {
      "name": ":)",
      "rank": 117,
      "level_score": 16170
    },
    {
      "name": "Vik†",
      "rank": 118,
      "level_score": 16167
    },
    {
      "name": "[DUVN].Blake",
      "rank": 119,
      "level_score": 16167
    },
    {
      "name": "FUTUREMAN",
      "rank": 120,
      "level_score": 16164
    },
    {
      "name": "MachineElf Steve",
      "rank": 121,
      "level_score": 16154
    },
    {
      "name": "Invisible",
      "rank": 122,
      "level_score": 16153
    },
    {
      "name": "nz",
      "rank": 123,
      "level_score": 16152
    },
    {
      "name": "CHUCK",
      "rank": 124,
      "level_score": 16150
    },
    {
      "name": "Old man 32 years old",
      "rank": 125,
      "level_score": 16147
    },
    {
      "name": "Only Lonely",
      "rank": 126,
      "level_score": 16145
    },
    {
      "name": "🐼🐼Kashll🐼🐼",
      "rank": 127,
      "level_score": 16140
    },
    {
      "name": "Daniryc",
      "rank": 128,
      "level_score": 16139
    },
    {
      "name": "ledung.bka",
      "rank": 129,
      "level_score": 16134
    },
    {
      "name": "chickabiddy0903",
      "rank": 130,
      "level_score": 16128
    },
    {
      "name": "☀阿驰",
      "rank": 131,
      "level_score": 16121
    },
    {
      "name": "valerazolotov",
      "rank": 132,
      "level_score": 16117
    },
    {
      "name": "Rambo!!!",
      "rank": 133,
      "level_score": 16114
    },
    {
      "name": "Cortana",
      "rank": 134,
      "level_score": 16112
    },
    {
      "name": "⭕⃤ ♕ R@ndom ♕",
      "rank": 135,
      "level_score": 16103
    },
    {
      "name": "1984",
      "rank": 136,
      "level_score": 16103
    },
    {
      "name": "怪化.猪上树",
      "rank": 137,
      "level_score": 16100
    },
    {
      "name": "Exile.Haiaosi.",
      "rank": 138,
      "level_score": 16096
    },
    {
      "name": "给我一泡尿的时间",
      "rank": 139,
      "level_score": 16082
    },
    {
      "name": "无心碰",
      "rank": 140,
      "level_score": 16070
    },
    {
      "name": "[DUVN].BangBang",
      "rank": 141,
      "level_score": 16068
    },
    {
      "name": "莓头莓脑",
      "rank": 142,
      "level_score": 16066
    },
    {
      "name": "76561198971725746",
      "rank": 143,
      "level_score": 16061
    },
    {
      "name": "[DUVN].Drphanductri",
      "rank": 144,
      "level_score": 16056
    },
    {
      "name": "范闲",
      "rank": 145,
      "level_score": 16053
    },
    {
      "name": "Чилаек поук",
      "rank": 146,
      "level_score": 16051
    },
    {
      "name": "Burden-",
      "rank": 147,
      "level_score": 16047
    },
    {
      "name": "Danger",
      "rank": 148,
      "level_score": 16047
    },
    {
      "name": "SCREAM",
      "rank": 149,
      "level_score": 16037
    },
    {
      "name": "全真道长.郝大通",
      "rank": 150,
      "level_score": 16032
    },
    {
      "name": "Sham",
      "rank": 151,
      "level_score": 16032
    },
    {
      "name": "TYLU",
      "rank": 152,
      "level_score": 16031
    },
    {
      "name": "Tengu",
      "rank": 153,
      "level_score": 16029
    },
    {
      "name": "TheSpoiledPrincess",
      "rank": 154,
      "level_score": 16025
    },
    {
      "name": "iMrJoke",
      "rank": 155,
      "level_score": 16017
    },
    {
      "name": "Canalia",
      "rank": 156,
      "level_score": 16008
    },
    {
      "name": "jordano",
      "rank": 157,
      "level_score": 15998
    },
    {
      "name": "面对疾风吧",
      "rank": 158,
      "level_score": 15996
    },
    {
      "name": "antonv022",
      "rank": 159,
      "level_score": 15996
    },
    {
      "name": "Каланын баласы",
      "rank": 160,
      "level_score": 15995
    },
    {
      "name": "7cking Mad",
      "rank": 161,
      "level_score": 15988
    },
    {
      "name": "NoFriend",
      "rank": 162,
      "level_score": 15972
    },
    {
      "name": "chelo",
      "rank": 163,
      "level_score": 15966
    },
    {
      "name": "Legendary",
      "rank": 164,
      "level_score": 15965
    },
    {
      "name": "WHATISTHIS?",
      "rank": 165,
      "level_score": 15961
    },
    {
      "name": "生きている",
      "rank": 166,
      "level_score": 15960
    },
    {
      "name": "SEEYEE",
      "rank": 167,
      "level_score": 15959
    },
    {
      "name": "Solitude'",
      "rank": 168,
      "level_score": 15957
    },
    {
      "name": "Karl",
      "rank": 169,
      "level_score": 15953
    },
    {
      "name": "JohnDragon",
      "rank": 170,
      "level_score": 15948
    },
    {
      "name": "Jaxxi",
      "rank": 171,
      "level_score": 15945
    },
    {
      "name": "(( ◣﹏◢))",
      "rank": 172,
      "level_score": 15944
    },
    {
      "name": "Where",
      "rank": 173,
      "level_score": 15943
    },
    {
      "name": "m.burdin",
      "rank": 174,
      "level_score": 15941
    },
    {
      "name": "Mecrens",
      "rank": 175,
      "level_score": 15934
    },
    {
      "name": "Limon",
      "rank": 176,
      "level_score": 15931
    },
    {
      "name": "[RED]murq1",
      "rank": 177,
      "level_score": 15931
    },
    {
      "name": "我稳的很",
      "rank": 178,
      "level_score": 15931
    },
    {
      "name": "Detalex22",
      "rank": 179,
      "level_score": 15930
    },
    {
      "name": "masturbinho76",
      "rank": 180,
      "level_score": 15929
    },
    {
      "name": "yuukimeh",
      "rank": 181,
      "level_score": 15924
    },
    {
      "name": "chokh9",
      "rank": 182,
      "level_score": 15916
    },
    {
      "name": "夕阳荫屋檐",
      "rank": 183,
      "level_score": 15915
    },
    {
      "name": "油尖旺金毛玲",
      "rank": 184,
      "level_score": 15910
    },
    {
      "name": "MiniBless",
      "rank": 185,
      "level_score": 15910
    },
    {
      "name": "VỊT",
      "rank": 186,
      "level_score": 15905
    },
    {
      "name": "ahmed.badah",
      "rank": 187,
      "level_score": 15905
    },
    {
      "name": "-_-",
      "rank": 188,
      "level_score": 15904
    },
    {
      "name": "KrowSea (黑白羽未)",
      "rank": 189,
      "level_score": 15904
    },
    {
      "name": "-Hoezai-",
      "rank": 190,
      "level_score": 15896
    },
    {
      "name": "Puuchuking",
      "rank": 191,
      "level_score": 15893
    },
    {
      "name": "dan",
      "rank": 192,
      "level_score": 15893
    },
    {
      "name": "Saha",
      "rank": 193,
      "level_score": 15890
    },
    {
      "name": "Jesus con Aegis",
      "rank": 194,
      "level_score": 15889
    },
    {
      "name": "[WT] -Weba-",
      "rank": 195,
      "level_score": 15884
    },
    {
      "name": "GodsMistake",
      "rank": 196,
      "level_score": 15883
    },
    {
      "name": "Elffran",
      "rank": 197,
      "level_score": 15883
    },
    {
      "name": "fenix",
      "rank": 198,
      "level_score": 15877
    },
    {
      "name": "NickyRomero",
      "rank": 199,
      "level_score": 15871
    },
    {
      "name": "ヴィタリーデーモン",
      "rank": 200,
      "level_score": 15866
    },
    {
      "name": "aLeX_№o6™",
      "rank": 201,
      "level_score": 15865
    },
    {
      "name": "ЛАДЕР=СМЭРТЬ",
      "rank": 202,
      "level_score": 15860
    },
    {
      "name": "axxxxxxxxx",
      "rank": 203,
      "level_score": 15856
    },
    {
      "name": "活久见",
      "rank": 204,
      "level_score": 15845
    },
    {
      "name": "AHUK",
      "rank": 205,
      "level_score": 15840
    },
    {
      "name": "AnnoyingNinjas",
      "rank": 206,
      "level_score": 15839
    },
    {
      "name": "Megasena",
      "rank": 207,
      "level_score": 15838
    },
    {
      "name": "ROFLMAOINMYSOUL",
      "rank": 208,
      "level_score": 15837
    },
    {
      "name": "Laylow",
      "rank": 209,
      "level_score": 15832
    },
    {
      "name": "The Lord",
      "rank": 210,
      "level_score": 15829
    },
    {
      "name": "Marceus",
      "rank": 211,
      "level_score": 15824
    },
    {
      "name": "kartmanjr",
      "rank": 212,
      "level_score": 15820
    },
    {
      "name": "大トロ！",
      "rank": 213,
      "level_score": 15815
    },
    {
      "name": "ldr",
      "rank": 214,
      "level_score": 15809
    },
    {
      "name": "Fløx",
      "rank": 215,
      "level_score": 15805
    },
    {
      "name": "Argaste",
      "rank": 216,
      "level_score": 15804
    },
    {
      "name": "Stand!n_red",
      "rank": 217,
      "level_score": 15804
    },
    {
      "name": "Gustav Babaev",
      "rank": 218,
      "level_score": 15797
    },
    {
      "name": "huoods",
      "rank": 219,
      "level_score": 15791
    },
    {
      "name": "POWER",
      "rank": 220,
      "level_score": 15788
    },
    {
      "name": "HOMEBOY",
      "rank": 221,
      "level_score": 15787
    },
    {
      "name": "【滅xDemon】",
      "rank": 222,
      "level_score": 15787
    },
    {
      "name": "boboyyy1998",
      "rank": 223,
      "level_score": 15786
    },
    {
      "name": "深海",
      "rank": 224,
      "level_score": 15781
    },
    {
      "name": "My man",
      "rank": 225,
      "level_score": 15778
    },
    {
      "name": "ZA WARUDO",
      "rank": 226,
      "level_score": 15765
    },
    {
      "name": "ANGG_MA4O",
      "rank": 227,
      "level_score": 15761
    },
    {
      "name": "kenigdan",
      "rank": 228,
      "level_score": 15752
    },
    {
      "name": "T.Tv/Goonikon",
      "rank": 229,
      "level_score": 15752
    },
    {
      "name": "vousmevoyez",
      "rank": 230,
      "level_score": 15751
    },
    {
      "name": "5ive.teoeleo",
      "rank": 231,
      "level_score": 15746
    },
    {
      "name": "jjjannes ☁",
      "rank": 232,
      "level_score": 15744
    },
    {
      "name": "NGX",
      "rank": 233,
      "level_score": 15743
    },
    {
      "name": "Yud Nah",
      "rank": 234,
      "level_score": 15742
    },
    {
      "name": "joshua_chan1",
      "rank": 235,
      "level_score": 15737
    },
    {
      "name": "SmosDerm3_NakNa",
      "rank": 236,
      "level_score": 15737
    },
    {
      "name": "Meiahhh___",
      "rank": 237,
      "level_score": 15735
    },
    {
      "name": "mRitamissu",
      "rank": 238,
      "level_score": 15733
    },
    {
      "name": "imbas",
      "rank": 239,
      "level_score": 15726
    },
    {
      "name": "GLORIOUS",
      "rank": 240,
      "level_score": 15725
    },
    {
      "name": "W36 - URSS -  HC",
      "rank": 241,
      "level_score": 15724
    },
    {
      "name": "kiry900",
      "rank": 242,
      "level_score": 15723
    },
    {
      "name": "Monaka",
      "rank": 243,
      "level_score": 15723
    },
    {
      "name": "Frolik6767",
      "rank": 244,
      "level_score": 15719
    },
    {
      "name": "Makoto",
      "rank": 245,
      "level_score": 15719
    },
    {
      "name": "白嫖怪",
      "rank": 246,
      "level_score": 15718
    },
    {
      "name": "Frankel",
      "rank": 247,
      "level_score": 15716
    },
    {
      "name": "SaF",
      "rank": 248,
      "level_score": 15712
    },
    {
      "name": "Moskva?  privet?",
      "rank": 249,
      "level_score": 15703
    },
    {
      "name": "yogadustar",
      "rank": 250,
      "level_score": 15693
    },
    {
      "name": "76561198124396588",
      "rank": 251,
      "level_score": 15692
    },
    {
      "name": "efr",
      "rank": 252,
      "level_score": 15684
    },
    {
      "name": "tatapuh33",
      "rank": 253,
      "level_score": 15680
    },
    {
      "name": "MMM",
      "rank": 254,
      "level_score": 15678
    },
    {
      "name": "Vy vy ♕",
      "rank": 255,
      "level_score": 15678
    },
    {
      "name": "Адмирал СнупДог",
      "rank": 256,
      "level_score": 15674
    },
    {
      "name": "雅各布",
      "rank": 257,
      "level_score": 15674
    },
    {
      "name": "Jīv Jāgo",
      "rank": 258,
      "level_score": 15674
    },
    {
      "name": "The Chazz",
      "rank": 259,
      "level_score": 15670
    },
    {
      "name": "tawiwat.s",
      "rank": 260,
      "level_score": 15665
    },
    {
      "name": "spartak moscow",
      "rank": 261,
      "level_score": 15663
    },
    {
      "name": "BRAWNY",
      "rank": 262,
      "level_score": 15658
    },
    {
      "name": "Kyan",
      "rank": 263,
      "level_score": 15653
    },
    {
      "name": "Old Gregg",
      "rank": 264,
      "level_score": 15648
    },
    {
      "name": "白鹿原",
      "rank": 265,
      "level_score": 15644
    },
    {
      "name": "SIV",
      "rank": 266,
      "level_score": 15641
    },
    {
      "name": "Achilles",
      "rank": 267,
      "level_score": 15638
    },
    {
      "name": "Чекающий стату",
      "rank": 268,
      "level_score": 15634
    },
    {
      "name": "ddl.afood",
      "rank": 269,
      "level_score": 15629
    },
    {
      "name": "Pussy",
      "rank": 270,
      "level_score": 15627
    },
    {
      "name": "我是个机器人",
      "rank": 271,
      "level_score": 15626
    },
    {
      "name": "KOZAK BOGDAN",
      "rank": 272,
      "level_score": 15624
    },
    {
      "name": "Asakura YoYo",
      "rank": 273,
      "level_score": 15623
    },
    {
      "name": "Бок доты",
      "rank": 274,
      "level_score": 15617
    },
    {
      "name": "Soulsilver",
      "rank": 275,
      "level_score": 15615
    },
    {
      "name": "毙梨",
      "rank": 276,
      "level_score": 15615
    },
    {
      "name": "jesusatanchrist",
      "rank": 277,
      "level_score": 15611
    },
    {
      "name": "Kapitoshich",
      "rank": 278,
      "level_score": 15606
    },
    {
      "name": "jama",
      "rank": 279,
      "level_score": 15598
    },
    {
      "name": "vic",
      "rank": 280,
      "level_score": 15597
    },
    {
      "name": "v2543",
      "rank": 281,
      "level_score": 15594
    },
    {
      "name": "Persulit",
      "rank": 282,
      "level_score": 15589
    },
    {
      "name": "jOe",
      "rank": 283,
      "level_score": 15586
    },
    {
      "name": "Jho Low",
      "rank": 284,
      "level_score": 15585
    },
    {
      "name": "SnarfWhooozle",
      "rank": 285,
      "level_score": 15585
    },
    {
      "name": "Marry Haguire",
      "rank": 286,
      "level_score": 15583
    },
    {
      "name": "nyps",
      "rank": 287,
      "level_score": 15577
    },
    {
      "name": "Plan C",
      "rank": 288,
      "level_score": 15574
    },
    {
      "name": "Itna",
      "rank": 289,
      "level_score": 15573
    },
    {
      "name": "Selemene",
      "rank": 290,
      "level_score": 15569
    },
    {
      "name": "gussypuci",
      "rank": 291,
      "level_score": 15567
    },
    {
      "name": "sk1lyab0b41Q",
      "rank": 292,
      "level_score": 15565
    },
    {
      "name": "qws",
      "rank": 293,
      "level_score": 15560
    },
    {
      "name": "Sylar19",
      "rank": 294,
      "level_score": 15552
    },
    {
      "name": "Kalan",
      "rank": 295,
      "level_score": 15549
    },
    {
      "name": "Ersee",
      "rank": 296,
      "level_score": 15549
    },
    {
      "name": "SPQvisagChen",
      "rank": 297,
      "level_score": 15549
    },
    {
      "name": "Думать вредно",
      "rank": 298,
      "level_score": 15547
    },
    {
      "name": "怪化.月半子",
      "rank": 299,
      "level_score": 15542
    },
    {
      "name": "bek_unit",
      "rank": 300,
      "level_score": 15542
    },
    {
      "name": "B1@ćķ",
      "rank": 301,
      "level_score": 15541
    },
    {
      "name": "Grindan",
      "rank": 302,
      "level_score": 15540
    },
    {
      "name": "fxxxxxxxxxxxxxxxxxking",
      "rank": 303,
      "level_score": 15535
    },
    {
      "name": "我说你藓你就藓",
      "rank": 304,
      "level_score": 15535
    },
    {
      "name": "SupaturQ",
      "rank": 305,
      "level_score": 15524
    },
    {
      "name": "#BOYCOTTANIMERUSSIANS",
      "rank": 306,
      "level_score": 15523
    },
    {
      "name": "YouChizzz",
      "rank": 307,
      "level_score": 15522
    },
    {
      "name": "凭什么和我打~",
      "rank": 308,
      "level_score": 15520
    },
    {
      "name": "Yogi_PaToLa",
      "rank": 309,
      "level_score": 15518
    },
    {
      "name": "A?",
      "rank": 310,
      "level_score": 15514
    },
    {
      "name": "你怎么知道我是大师",
      "rank": 311,
      "level_score": 15509
    },
    {
      "name": "Ginjio",
      "rank": 312,
      "level_score": 15504
    },
    {
      "name": "Shop Keeper",
      "rank": 313,
      "level_score": 15496
    },
    {
      "name": "gastly8787",
      "rank": 314,
      "level_score": 15495
    },
    {
      "name": "LUCIFER666",
      "rank": 315,
      "level_score": 15494
    },
    {
      "name": "[WT] cem",
      "rank": 316,
      "level_score": 15492
    },
    {
      "name": "oppo",
      "rank": 317,
      "level_score": 15492
    },
    {
      "name": "TH3 KING SL4YER",
      "rank": 318,
      "level_score": 15487
    },
    {
      "name": "CHEROKATOR",
      "rank": 319,
      "level_score": 15480
    },
    {
      "name": "anthihong.le",
      "rank": 320,
      "level_score": 15477
    },
    {
      "name": "Чорт",
      "rank": 321,
      "level_score": 15477
    },
    {
      "name": "虎校",
      "rank": 322,
      "level_score": 15476
    },
    {
      "name": "Zipse",
      "rank": 323,
      "level_score": 15470
    },
    {
      "name": "Турбобой",
      "rank": 324,
      "level_score": 15468
    },
    {
      "name": "F3ejtJutd",
      "rank": 325,
      "level_score": 15466
    },
    {
      "name": "bored",
      "rank": 326,
      "level_score": 15465
    },
    {
      "name": "1002999685",
      "rank": 327,
      "level_score": 15463
    },
    {
      "name": "Got",
      "rank": 328,
      "level_score": 15457
    },
    {
      "name": "123",
      "rank": 329,
      "level_score": 15453
    },
    {
      "name": "bae.oo",
      "rank": 330,
      "level_score": 15446
    },
    {
      "name": "司命",
      "rank": 331,
      "level_score": 15444
    },
    {
      "name": "am_lifeguard",
      "rank": 332,
      "level_score": 15439
    },
    {
      "name": "maxrodriguesunp",
      "rank": 333,
      "level_score": 15436
    },
    {
      "name": "Crazy hawaiian",
      "rank": 334,
      "level_score": 15431
    },
    {
      "name": "Skeep",
      "rank": 335,
      "level_score": 15428
    },
    {
      "name": "SouJ",
      "rank": 336,
      "level_score": 15427
    },
    {
      "name": "sam",
      "rank": 337,
      "level_score": 15426
    },
    {
      "name": "TORPEDOTorsten",
      "rank": 338,
      "level_score": 15425
    },
    {
      "name": "gelge",
      "rank": 339,
      "level_score": 15424
    },
    {
      "name": "Prorul",
      "rank": 340,
      "level_score": 15420
    },
    {
      "name": "真 系  2 B",
      "rank": 341,
      "level_score": 15419
    },
    {
      "name": "老头.莫兰特",
      "rank": 342,
      "level_score": 15414
    },
    {
      "name": "Jo333",
      "rank": 343,
      "level_score": 15408
    },
    {
      "name": "Everything grows with love",
      "rank": 344,
      "level_score": 15407
    },
    {
      "name": "~SuxZ",
      "rank": 345,
      "level_score": 15405
    },
    {
      "name": "Homunculus`",
      "rank": 346,
      "level_score": 15403
    },
    {
      "name": "Steve",
      "rank": 347,
      "level_score": 15401
    },
    {
      "name": "空桑花",
      "rank": 348,
      "level_score": 15399
    },
    {
      "name": "GroBeFa",
      "rank": 349,
      "level_score": 15399
    },
    {
      "name": "VITO",
      "rank": 350,
      "level_score": 15392
    },
    {
      "name": "Ёжик",
      "rank": 351,
      "level_score": 15390
    },
    {
      "name": "当妈把妹手",
      "rank": 352,
      "level_score": 15388
    },
    {
      "name": "Olympic",
      "rank": 353,
      "level_score": 15388
    },
    {
      "name": "Самуил Эл Джексон",
      "rank": 354,
      "level_score": 15384
    },
    {
      "name": "poTTie",
      "rank": 355,
      "level_score": 15382
    },
    {
      "name": "Pussyrocker",
      "rank": 356,
      "level_score": 15380
    },
    {
      "name": "KiriKhan",
      "rank": 357,
      "level_score": 15378
    },
    {
      "name": "SIR BAUDELAIRE",
      "rank": 358,
      "level_score": 15377
    },
    {
      "name": "DedMoroz",
      "rank": 359,
      "level_score": 15366
    },
    {
      "name": "Hellboy",
      "rank": 360,
      "level_score": 15363
    },
    {
      "name": "✪︎ Nika",
      "rank": 361,
      "level_score": 15363
    },
    {
      "name": "Паровозик которы",
      "rank": 362,
      "level_score": 15361
    },
    {
      "name": "puppyeyesivan",
      "rank": 363,
      "level_score": 15360
    },
    {
      "name": "有点紧张",
      "rank": 364,
      "level_score": 15357
    },
    {
      "name": "32",
      "rank": 365,
      "level_score": 15355
    },
    {
      "name": "iREF",
      "rank": 366,
      "level_score": 15355
    },
    {
      "name": "tronglong88",
      "rank": 367,
      "level_score": 15353
    },
    {
      "name": "greenbird13",
      "rank": 368,
      "level_score": 15352
    },
    {
      "name": "Nest",
      "rank": 369,
      "level_score": 15345
    },
    {
      "name": "Kelmi",
      "rank": 370,
      "level_score": 15344
    },
    {
      "name": "开局操作猛如虎 一看Carr",
      "rank": 371,
      "level_score": 15342
    },
    {
      "name": "WinBabyHack",
      "rank": 372,
      "level_score": 15342
    },
    {
      "name": "menymenks",
      "rank": 373,
      "level_score": 15341
    },
    {
      "name": "Instinct*",
      "rank": 374,
      "level_score": 15340
    },
    {
      "name": "nk6gpc",
      "rank": 375,
      "level_score": 15340
    },
    {
      "name": "Mj",
      "rank": 376,
      "level_score": 15340
    },
    {
      "name": "棋鸡",
      "rank": 377,
      "level_score": 15340
    },
    {
      "name": "kirya sueta",
      "rank": 378,
      "level_score": 15340
    },
    {
      "name": "二大爷",
      "rank": 379,
      "level_score": 15337
    },
    {
      "name": "Ha!89",
      "rank": 380,
      "level_score": 15337
    },
    {
      "name": "影子",
      "rank": 381,
      "level_score": 15332
    },
    {
      "name": "BUY AAPL",
      "rank": 382,
      "level_score": 15331
    },
    {
      "name": "一蓑烟雨",
      "rank": 383,
      "level_score": 15329
    },
    {
      "name": "FB`[УбивашКа]",
      "rank": 384,
      "level_score": 15321
    },
    {
      "name": "Se7eN",
      "rank": 385,
      "level_score": 15319
    },
    {
      "name": "习溪桥第一靓仔",
      "rank": 386,
      "level_score": 15314
    },
    {
      "name": "♠ Joker- ♥",
      "rank": 387,
      "level_score": 15313
    },
    {
      "name": "laccone",
      "rank": 388,
      "level_score": 15300
    },
    {
      "name": "urugvaec",
      "rank": 389,
      "level_score": 15299
    },
    {
      "name": "noobfrommur",
      "rank": 390,
      "level_score": 15299
    },
    {
      "name": "ShtekeR",
      "rank": 391,
      "level_score": 15298
    },
    {
      "name": "WWW",
      "rank": 392,
      "level_score": 15295
    },
    {
      "name": "kolt",
      "rank": 393,
      "level_score": 15292
    },
    {
      "name": "GrumpyGardenGnome",
      "rank": 394,
      "level_score": 15292
    },
    {
      "name": "Pingu",
      "rank": 395,
      "level_score": 15289
    },
    {
      "name": "Артём Тащинский",
      "rank": 396,
      "level_score": 15285
    },
    {
      "name": "7292247aj",
      "rank": 397,
      "level_score": 15284
    },
    {
      "name": "Bentooooo",
      "rank": 398,
      "level_score": 15283
    },
    {
      "name": "buiphutrung1991",
      "rank": 399,
      "level_score": 15278
    },
    {
      "name": "Tremolo91",
      "rank": 400,
      "level_score": 15274
    },
    {
      "name": "Random.",
      "rank": 401,
      "level_score": 15269
    },
    {
      "name": "Tha Khin Khaw",
      "rank": 402,
      "level_score": 15267
    },
    {
      "name": "FeDuke",
      "rank": 403,
      "level_score": 15264
    },
    {
      "name": "Isun",
      "rank": 404,
      "level_score": 15260
    },
    {
      "name": "(f)Armin Van Buuren",
      "rank": 405,
      "level_score": 15256
    },
    {
      "name": "Let'sGoBrandon!",
      "rank": 406,
      "level_score": 15256
    },
    {
      "name": "Brutto-Adidas",
      "rank": 407,
      "level_score": 15256
    },
    {
      "name": "croweffect",
      "rank": 408,
      "level_score": 15255
    },
    {
      "name": "lord jumong",
      "rank": 409,
      "level_score": 15254
    },
    {
      "name": "Jay Temple",
      "rank": 410,
      "level_score": 15252
    },
    {
      "name": "DrS",
      "rank": 411,
      "level_score": 15248
    },
    {
      "name": "SuperBizonReturn",
      "rank": 412,
      "level_score": 15245
    },
    {
      "name": "Mihail Abagiu",
      "rank": 413,
      "level_score": 15240
    },
    {
      "name": "偷乐时刻",
      "rank": 414,
      "level_score": 15239
    },
    {
      "name": "Oh Ho !!!!!",
      "rank": 415,
      "level_score": 15238
    },
    {
      "name": "Teeeeern",
      "rank": 416,
      "level_score": 15237
    },
    {
      "name": "LeProfDeGrigny",
      "rank": 417,
      "level_score": 15231
    },
    {
      "name": "大麻强",
      "rank": 418,
      "level_score": 15231
    },
    {
      "name": "Katsudon",
      "rank": 419,
      "level_score": 15228
    },
    {
      "name": "susbaby",
      "rank": 420,
      "level_score": 15227
    },
    {
      "name": "哪里来的自信？",
      "rank": 421,
      "level_score": 15226
    },
    {
      "name": "Aiov",
      "rank": 422,
      "level_score": 15226
    },
    {
      "name": "TIRION",
      "rank": 423,
      "level_score": 15223
    },
    {
      "name": "dm1tr9x ™ ►†◄",
      "rank": 424,
      "level_score": 15223
    },
    {
      "name": "Citizen:Dane",
      "rank": 425,
      "level_score": 15222
    },
    {
      "name": "BradfordLee",
      "rank": 426,
      "level_score": 15221
    },
    {
      "name": "anton_bringeland",
      "rank": 427,
      "level_score": 15220
    },
    {
      "name": "Sdrumo",
      "rank": 428,
      "level_score": 15220
    },
    {
      "name": "BEmine",
      "rank": 429,
      "level_score": 15218
    },
    {
      "name": "四川2套",
      "rank": 430,
      "level_score": 15216
    },
    {
      "name": "dota222",
      "rank": 431,
      "level_score": 15214
    },
    {
      "name": "Scaramouche",
      "rank": 432,
      "level_score": 15211
    },
    {
      "name": "Twistd",
      "rank": 433,
      "level_score": 15204
    },
    {
      "name": "改名保天胡",
      "rank": 434,
      "level_score": 15200
    },
    {
      "name": "vutbank",
      "rank": 435,
      "level_score": 15198
    },
    {
      "name": "Mercurial",
      "rank": 436,
      "level_score": 15198
    },
    {
      "name": "Feigr",
      "rank": 437,
      "level_score": 15198
    },
    {
      "name": "BawlinBalkanBrotha",
      "rank": 438,
      "level_score": 15195
    },
    {
      "name": "Bruce羅",
      "rank": 439,
      "level_score": 15194
    },
    {
      "name": "ENKI KORN",
      "rank": 440,
      "level_score": 15192
    },
    {
      "name": "R u OK ?",
      "rank": 441,
      "level_score": 15190
    },
    {
      "name": "striker420",
      "rank": 442,
      "level_score": 15188
    },
    {
      "name": "RudeBoy",
      "rank": 443,
      "level_score": 15187
    },
    {
      "name": "the Korean ZOMBIE",
      "rank": 444,
      "level_score": 15186
    },
    {
      "name": "льван болван",
      "rank": 445,
      "level_score": 15185
    },
    {
      "name": "ssfs",
      "rank": 446,
      "level_score": 15180
    },
    {
      "name": "Илилень",
      "rank": 447,
      "level_score": 15180
    },
    {
      "name": "内秘心书PRO",
      "rank": 448,
      "level_score": 15179
    },
    {
      "name": "ŁỚŠŦ2217",
      "rank": 449,
      "level_score": 15179
    },
    {
      "name": "暴怒火神一笑",
      "rank": 450,
      "level_score": 15177
    },
    {
      "name": "MaMieHigh",
      "rank": 451,
      "level_score": 15172
    },
    {
      "name": "wei",
      "rank": 452,
      "level_score": 15171
    },
    {
      "name": "Blackcoffe",
      "rank": 453,
      "level_score": 15166
    },
    {
      "name": "GooseFraba",
      "rank": 454,
      "level_score": 15165
    },
    {
      "name": "老年选手",
      "rank": 455,
      "level_score": 15164
    },
    {
      "name": "Quỷ zữ 666",
      "rank": 456,
      "level_score": 15162
    },
    {
      "name": "Lolipap",
      "rank": 457,
      "level_score": 15160
    },
    {
      "name": "I_Lone",
      "rank": 458,
      "level_score": 15159
    },
    {
      "name": "host 5x5 aptb",
      "rank": 459,
      "level_score": 15159
    },
    {
      "name": "Feks0531",
      "rank": 460,
      "level_score": 15158
    },
    {
      "name": "rybakov.e.a",
      "rank": 461,
      "level_score": 15155
    },
    {
      "name": "tushhhh",
      "rank": 462,
      "level_score": 15155
    },
    {
      "name": "Albert Kekstein",
      "rank": 463,
      "level_score": 15155
    },
    {
      "name": "转眼四十已有一",
      "rank": 464,
      "level_score": 15154
    },
    {
      "name": "划就是了",
      "rank": 465,
      "level_score": 15154
    },
    {
      "name": "alexe",
      "rank": 466,
      "level_score": 15153
    },
    {
      "name": "Osuus",
      "rank": 467,
      "level_score": 15153
    },
    {
      "name": "p!s<e$",
      "rank": 468,
      "level_score": 15149
    },
    {
      "name": "NeAngel",
      "rank": 469,
      "level_score": 15145
    },
    {
      "name": "Somberlain",
      "rank": 470,
      "level_score": 15142
    },
    {
      "name": "Thugss",
      "rank": 471,
      "level_score": 15142
    },
    {
      "name": "It's Showtime",
      "rank": 472,
      "level_score": 15141
    },
    {
      "name": "xiaoxiao904",
      "rank": 473,
      "level_score": 15139
    },
    {
      "name": "ka4",
      "rank": 474,
      "level_score": 15139
    },
    {
      "name": "R A G E",
      "rank": 475,
      "level_score": 15137
    },
    {
      "name": "FeeeeL",
      "rank": 476,
      "level_score": 15134
    },
    {
      "name": "jepsilogo",
      "rank": 477,
      "level_score": 15132
    },
    {
      "name": "компадро комбоко",
      "rank": 478,
      "level_score": 15132
    },
    {
      "name": "Bosh",
      "rank": 479,
      "level_score": 15132
    },
    {
      "name": "CHANG",
      "rank": 480,
      "level_score": 15126
    },
    {
      "name": "twistedgrip",
      "rank": 481,
      "level_score": 15125
    },
    {
      "name": "Shiro",
      "rank": 482,
      "level_score": 15122
    },
    {
      "name": "KarpenkoSSS",
      "rank": 483,
      "level_score": 15120
    },
    {
      "name": "truongloi0507",
      "rank": 484,
      "level_score": 15119
    },
    {
      "name": "corywatch",
      "rank": 485,
      "level_score": 15118
    },
    {
      "name": "блэк мамба",
      "rank": 486,
      "level_score": 15117
    },
    {
      "name": "SavvZoR The Escape Artist",
      "rank": 487,
      "level_score": 15112
    },
    {
      "name": "HP_Thieugia",
      "rank": 488,
      "level_score": 15111
    },
    {
      "name": "NLCI",
      "rank": 489,
      "level_score": 15109
    },
    {
      "name": "*Streame",
      "rank": 490,
      "level_score": 15108
    },
    {
      "name": "QM_Snipskii",
      "rank": 491,
      "level_score": 15108
    },
    {
      "name": "Blizzr",
      "rank": 492,
      "level_score": 15107
    },
    {
      "name": "Rizmo",
      "rank": 493,
      "level_score": 15106
    },
    {
      "name": "1vv1",
      "rank": 494,
      "level_score": 15105
    },
    {
      "name": "tcshka",
      "rank": 495,
      "level_score": 15104
    },
    {
      "name": "Amidamaru",
      "rank": 496,
      "level_score": 15102
    },
    {
      "name": "Girthquake",
      "rank": 497,
      "level_score": 15101
    },
    {
      "name": "Как сумел так сыг",
      "rank": 498,
      "level_score": 15098
    },
    {
      "name": "KAIJIN CORPORATION",
      "rank": 499,
      "level_score": 15098
    },
    {
      "name": "kvothe",
      "rank": 500,
      "level_score": 15098
    },
    {
      "name": "TheBlackReaper",
      "rank": 501,
      "level_score": 15096
    },
    {
      "name": "PrinceCYrus",
      "rank": 502,
      "level_score": 15095
    },
    {
      "name": "QTBadBoi - Still Cute. And bad.",
      "rank": 503,
      "level_score": 15093
    },
    {
      "name": "蜀山拳击卡",
      "rank": 504,
      "level_score": 15092
    },
    {
      "name": "ДИМASSS",
      "rank": 505,
      "level_score": 15088
    },
    {
      "name": "EW3F.StalkeR",
      "rank": 506,
      "level_score": 15087
    },
    {
      "name": "Gankmemore",
      "rank": 507,
      "level_score": 15087
    },
    {
      "name": "kane",
      "rank": 508,
      "level_score": 15086
    },
    {
      "name": "Mysteryom",
      "rank": 509,
      "level_score": 15085
    },
    {
      "name": "banhcanhchobong",
      "rank": 510,
      "level_score": 15085
    },
    {
      "name": "BUD LIGHT",
      "rank": 511,
      "level_score": 15084
    },
    {
      "name": "Makaveli",
      "rank": 512,
      "level_score": 15083
    },
    {
      "name": "Z-V",
      "rank": 513,
      "level_score": 15083
    },
    {
      "name": "Александр Пичушк",
      "rank": 514,
      "level_score": 15081
    },
    {
      "name": "霸业帅小伙",
      "rank": 515,
      "level_score": 15080
    },
    {
      "name": "西安项少龙",
      "rank": 516,
      "level_score": 15080
    },
    {
      "name": "Lobster",
      "rank": 517,
      "level_score": 15079
    },
    {
      "name": "EggTrần",
      "rank": 518,
      "level_score": 15076
    },
    {
      "name": "骑猪观海",
      "rank": 519,
      "level_score": 15074
    },
    {
      "name": "Cupcake",
      "rank": 520,
      "level_score": 15073
    },
    {
      "name": "闪电侠丁丁",
      "rank": 521,
      "level_score": 15073
    },
    {
      "name": "M4gn3t im Kopf",
      "rank": 522,
      "level_score": 15071
    },
    {
      "name": "MAMENG <3♪",
      "rank": 523,
      "level_score": 15069
    },
    {
      "name": "Chika",
      "rank": 524,
      "level_score": 15069
    },
    {
      "name": "Soa爷",
      "rank": 525,
      "level_score": 15068
    },
    {
      "name": "Азамат Мусагалие",
      "rank": 526,
      "level_score": 15066
    },
    {
      "name": "SalamoN",
      "rank": 527,
      "level_score": 15065
    },
    {
      "name": "darkguide",
      "rank": 528,
      "level_score": 15065
    },
    {
      "name": "coacolojl",
      "rank": 529,
      "level_score": 15065
    },
    {
      "name": "Hronus",
      "rank": 530,
      "level_score": 15061
    },
    {
      "name": "<<<NoVoHYDoNoSoR>>>",
      "rank": 531,
      "level_score": 15060
    },
    {
      "name": "k4m1n4r1",
      "rank": 532,
      "level_score": 15059
    },
    {
      "name": "TudiDudi",
      "rank": 533,
      "level_score": 15058
    },
    {
      "name": "Lümmler",
      "rank": 534,
      "level_score": 15055
    },
    {
      "name": "civikfirefly",
      "rank": 535,
      "level_score": 15053
    },
    {
      "name": "Spiritual's Ritual™",
      "rank": 536,
      "level_score": 15052
    },
    {
      "name": "MuurarinEno",
      "rank": 537,
      "level_score": 15051
    },
    {
      "name": "Nyaaa",
      "rank": 538,
      "level_score": 15051
    },
    {
      "name": "tv/DanSer_",
      "rank": 539,
      "level_score": 15050
    },
    {
      "name": "necrozavr",
      "rank": 540,
      "level_score": 15047
    },
    {
      "name": "!!!",
      "rank": 541,
      "level_score": 15045
    },
    {
      "name": "bloodthiRsty",
      "rank": 542,
      "level_score": 15043
    },
    {
      "name": "halinorath",
      "rank": 543,
      "level_score": 15042
    },
    {
      "name": "Vollies",
      "rank": 544,
      "level_score": 15039
    },
    {
      "name": "BOJAR",
      "rank": 545,
      "level_score": 15037
    },
    {
      "name": "Nhân Phẩm Như Cứt",
      "rank": 546,
      "level_score": 15037
    },
    {
      "name": "ambs",
      "rank": 547,
      "level_score": 15037
    },
    {
      "name": "746",
      "rank": 548,
      "level_score": 15035
    },
    {
      "name": "High af xD",
      "rank": 549,
      "level_score": 15034
    },
    {
      "name": "Torrasque",
      "rank": 550,
      "level_score": 15032
    },
    {
      "name": "放开那个妹纸",
      "rank": 551,
      "level_score": 15031
    },
    {
      "name": "diazdiazov87",
      "rank": 552,
      "level_score": 15031
    },
    {
      "name": "MUNDUT’z",
      "rank": 553,
      "level_score": 15030
    },
    {
      "name": "w1tchboy",
      "rank": 554,
      "level_score": 15029
    },
    {
      "name": "杀金老大",
      "rank": 555,
      "level_score": 15028
    },
    {
      "name": "mr.Borsch",
      "rank": 556,
      "level_score": 15027
    },
    {
      "name": "awikwok",
      "rank": 557,
      "level_score": 15026
    },
    {
      "name": "HellRoy",
      "rank": 558,
      "level_score": 15026
    },
    {
      "name": "WaterMan",
      "rank": 559,
      "level_score": 15025
    },
    {
      "name": "HOBO灬",
      "rank": 560,
      "level_score": 15024
    },
    {
      "name": "Ragnar Lothbrok",
      "rank": 561,
      "level_score": 15023
    },
    {
      "name": "Кэп",
      "rank": 562,
      "level_score": 15022
    },
    {
      "name": "CASPER_10",
      "rank": 563,
      "level_score": 15022
    },
    {
      "name": "Konrad Konfident",
      "rank": 564,
      "level_score": 15022
    },
    {
      "name": "Choi Yena",
      "rank": 565,
      "level_score": 15022
    },
    {
      "name": "kRU7CH",
      "rank": 566,
      "level_score": 15021
    },
    {
      "name": "studens",
      "rank": 567,
      "level_score": 15020
    },
    {
      "name": "Horst Seehofer",
      "rank": 568,
      "level_score": 15019
    },
    {
      "name": "Madoka",
      "rank": 569,
      "level_score": 15019
    },
    {
      "name": "777GlinnoMessi777",
      "rank": 570,
      "level_score": 15018
    },
    {
      "name": "Ghost",
      "rank": 571,
      "level_score": 15017
    },
    {
      "name": "lexakot2104",
      "rank": 572,
      "level_score": 15016
    },
    {
      "name": "loKi",
      "rank": 573,
      "level_score": 15015
    },
    {
      "name": "ilyxa",
      "rank": 574,
      "level_score": 15015
    },
    {
      "name": "Noobmaster69",
      "rank": 575,
      "level_score": 15014
    },
    {
      "name": "X",
      "rank": 576,
      "level_score": 15012
    },
    {
      "name": "VENOM",
      "rank": 577,
      "level_score": 15012
    },
    {
      "name": "---TrIpOdOtEr---",
      "rank": 578,
      "level_score": 15011
    },
    {
      "name": "( ^ o ^ )",
      "rank": 579,
      "level_score": 15011
    },
    {
      "name": "Burping",
      "rank": 580,
      "level_score": 15010
    },
    {
      "name": "935114680",
      "rank": 581,
      "level_score": 15009
    },
    {
      "name": "Magister Crazy",
      "rank": 582,
      "level_score": 15008
    },
    {
      "name": "Володя",
      "rank": 583,
      "level_score": 15008
    },
    {
      "name": "反弹我所有伤害",
      "rank": 584,
      "level_score": 15008
    },
    {
      "name": "Преисполненный",
      "rank": 585,
      "level_score": 15007
    },
    {
      "name": "★ Malika",
      "rank": 586,
      "level_score": 15007
    },
    {
      "name": "BearBrand",
      "rank": 587,
      "level_score": 15004
    },
    {
      "name": "BsaMBist",
      "rank": 588,
      "level_score": 15003
    },
    {
      "name": "βðardεr ву ηαтυяє",
      "rank": 589,
      "level_score": 15002
    },
    {
      "name": "Ambeyen",
      "rank": 590,
      "level_score": 15000
    },
    {
      "name": "boomcud49",
      "rank": 591,
      "level_score": 15000
    },
    {
      "name": "Dilanuyil",
      "rank": 592,
      "level_score": 14999
    },
    {
      "name": "QuickSilver",
      "rank": 593,
      "level_score": 14998
    },
    {
      "name": "Hắc Mười",
      "rank": 594,
      "level_score": 14998
    },
    {
      "name": "Furjko",
      "rank": 595,
      "level_score": 14997
    },
    {
      "name": "Курлык",
      "rank": 596,
      "level_score": 14993
    },
    {
      "name": "TIGREE COMEBACK",
      "rank": 597,
      "level_score": 14992
    },
    {
      "name": "Toxiprout",
      "rank": 598,
      "level_score": 14991
    },
    {
      "name": "soundchaosdebug",
      "rank": 599,
      "level_score": 14989
    },
    {
      "name": "mx310",
      "rank": 600,
      "level_score": 14988
    },
    {
      "name": "呵呵。。。",
      "rank": 601,
      "level_score": 14986
    },
    {
      "name": "Ђ_ล_Đ_я_Ĥ",
      "rank": 602,
      "level_score": 14983
    },
    {
      "name": "ocl",
      "rank": 603,
      "level_score": 14983
    },
    {
      "name": "Hovno kleslo",
      "rank": 604,
      "level_score": 14982
    },
    {
      "name": "MIDAS",
      "rank": 605,
      "level_score": 14982
    },
    {
      "name": "rèber",
      "rank": 606,
      "level_score": 14981
    },
    {
      "name": "Harald II.",
      "rank": 607,
      "level_score": 14980
    },
    {
      "name": "///",
      "rank": 608,
      "level_score": 14979
    },
    {
      "name": "professional varus player",
      "rank": 609,
      "level_score": 14978
    },
    {
      "name": "Agis",
      "rank": 610,
      "level_score": 14977
    },
    {
      "name": "βΘδδΨ",
      "rank": 611,
      "level_score": 14977
    },
    {
      "name": "Mozart_#",
      "rank": 612,
      "level_score": 14976
    },
    {
      "name": "jadist",
      "rank": 613,
      "level_score": 14973
    },
    {
      "name": "3Digits!!!!!!!",
      "rank": 614,
      "level_score": 14972
    },
    {
      "name": "Cycorn",
      "rank": 615,
      "level_score": 14971
    },
    {
      "name": "megasonyc",
      "rank": 616,
      "level_score": 14970
    },
    {
      "name": "ibejennyy",
      "rank": 617,
      "level_score": 14967
    },
    {
      "name": "ameame",
      "rank": 618,
      "level_score": 14966
    },
    {
      "name": "「NS」H ɑ w κ",
      "rank": 619,
      "level_score": 14965
    },
    {
      "name": "Етита",
      "rank": 620,
      "level_score": 14961
    },
    {
      "name": "KYTY3OB",
      "rank": 621,
      "level_score": 14961
    },
    {
      "name": "Soto99",
      "rank": 622,
      "level_score": 14960
    },
    {
      "name": "Sir Charles",
      "rank": 623,
      "level_score": 14959
    },
    {
      "name": "$upreme*",
      "rank": 624,
      "level_score": 14957
    },
    {
      "name": "เด็กเดินไว",
      "rank": 625,
      "level_score": 14955
    },
    {
      "name": "ilya.n.semenchenko",
      "rank": 626,
      "level_score": 14955
    },
    {
      "name": "Titania",
      "rank": 627,
      "level_score": 14950
    },
    {
      "name": "OlDderTy.BAStard.",
      "rank": 628,
      "level_score": 14949
    },
    {
      "name": "levisyahurpamungkas",
      "rank": 629,
      "level_score": 14949
    },
    {
      "name": "lanny",
      "rank": 630,
      "level_score": 14948
    },
    {
      "name": "Roadrunner",
      "rank": 631,
      "level_score": 14948
    },
    {
      "name": "Đức.TrM",
      "rank": 632,
      "level_score": 14947
    },
    {
      "name": "DLLR",
      "rank": 633,
      "level_score": 14944
    },
    {
      "name": "女侠请留手",
      "rank": 634,
      "level_score": 14943
    },
    {
      "name": "ssullung",
      "rank": 635,
      "level_score": 14942
    },
    {
      "name": "Kraqma",
      "rank": 636,
      "level_score": 14939
    },
    {
      "name": "R.FLAGGed",
      "rank": 637,
      "level_score": 14936
    },
    {
      "name": "IRon FIStS",
      "rank": 638,
      "level_score": 14933
    },
    {
      "name": "Валера!!",
      "rank": 639,
      "level_score": 14932
    },
    {
      "name": "việt cộng sabotage",
      "rank": 640,
      "level_score": 14929
    },
    {
      "name": "人若无名便可专心练剑",
      "rank": 641,
      "level_score": 14928
    },
    {
      "name": "thotho4696",
      "rank": 642,
      "level_score": 14926
    },
    {
      "name": "Channdd",
      "rank": 643,
      "level_score": 14924
    },
    {
      "name": "fonikipoutsa",
      "rank": 644,
      "level_score": 14923
    },
    {
      "name": "Xplodead",
      "rank": 645,
      "level_score": 14922
    },
    {
      "name": "p1. Pai ta ON",
      "rank": 646,
      "level_score": 14917
    },
    {
      "name": "1985cur",
      "rank": 647,
      "level_score": 14912
    },
    {
      "name": "cyrus840",
      "rank": 648,
      "level_score": 14912
    },
    {
      "name": "Царь Гвидон",
      "rank": 649,
      "level_score": 14907
    },
    {
      "name": "top_shark",
      "rank": 650,
      "level_score": 14905
    },
    {
      "name": "Q",
      "rank": 651,
      "level_score": 14905
    },
    {
      "name": "Daws D. Devereux",
      "rank": 652,
      "level_score": 14897
    },
    {
      "name": "Mucky",
      "rank": 653,
      "level_score": 14897
    },
    {
      "name": "natsvlz",
      "rank": 654,
      "level_score": 14896
    },
    {
      "name": "Memory",
      "rank": 655,
      "level_score": 14893
    },
    {
      "name": "Pietjepizza",
      "rank": 656,
      "level_score": 14893
    },
    {
      "name": "bouncegw",
      "rank": 657,
      "level_score": 14893
    },
    {
      "name": "ⓉⒾⒼⒺⓇ™",
      "rank": 658,
      "level_score": 14892
    },
    {
      "name": "a little bit psycho",
      "rank": 659,
      "level_score": 14892
    },
    {
      "name": "Prozack",
      "rank": 660,
      "level_score": 14889
    },
    {
      "name": "Ozymandias",
      "rank": 661,
      "level_score": 14889
    },
    {
      "name": "Aerox",
      "rank": 662,
      "level_score": 14888
    },
    {
      "name": "Walien",
      "rank": 663,
      "level_score": 14888
    },
    {
      "name": "OgerTob",
      "rank": 664,
      "level_score": 14888
    },
    {
      "name": "yuiop",
      "rank": 665,
      "level_score": 14887
    },
    {
      "name": "Stardust Yeager",
      "rank": 666,
      "level_score": 14886
    },
    {
      "name": "Adobong TAE",
      "rank": 667,
      "level_score": 14885
    },
    {
      "name": "Whatchu Barkin",
      "rank": 668,
      "level_score": 14884
    },
    {
      "name": "tozoku27",
      "rank": 669,
      "level_score": 14884
    },
    {
      "name": "asdfplj",
      "rank": 670,
      "level_score": 14883
    },
    {
      "name": "Legendary.NA",
      "rank": 671,
      "level_score": 14882
    },
    {
      "name": "DAMN.",
      "rank": 672,
      "level_score": 14880
    },
    {
      "name": "IT-Rex",
      "rank": 673,
      "level_score": 14880
    },
    {
      "name": "опытный",
      "rank": 674,
      "level_score": 14880
    },
    {
      "name": "kc.co",
      "rank": 675,
      "level_score": 14879
    },
    {
      "name": "Parrocchetto",
      "rank": 676,
      "level_score": 14878
    },
    {
      "name": "Dragon",
      "rank": 677,
      "level_score": 14875
    },
    {
      "name": "coffebreath88",
      "rank": 678,
      "level_score": 14874
    },
    {
      "name": "♡Nezuko♡",
      "rank": 679,
      "level_score": 14874
    },
    {
      "name": "Ronan",
      "rank": 680,
      "level_score": 14873
    },
    {
      "name": "Skooba",
      "rank": 681,
      "level_score": 14871
    },
    {
      "name": "digitalsun",
      "rank": 682,
      "level_score": 14865
    },
    {
      "name": "SpoonLight",
      "rank": 683,
      "level_score": 14864
    },
    {
      "name": "SantaCasa",
      "rank": 684,
      "level_score": 14863
    },
    {
      "name": "X/WheatCakes",
      "rank": 685,
      "level_score": 14862
    },
    {
      "name": "Shir Kahn",
      "rank": 686,
      "level_score": 14862
    },
    {
      "name": "Mendacium",
      "rank": 687,
      "level_score": 14861
    },
    {
      "name": "second mouse gets the cheese",
      "rank": 688,
      "level_score": 14860
    },
    {
      "name": "除膜慰道",
      "rank": 689,
      "level_score": 14859
    },
    {
      "name": "Лично_не_Бот",
      "rank": 690,
      "level_score": 14856
    },
    {
      "name": "BENZEMABALLOND'OR",
      "rank": 691,
      "level_score": 14853
    },
    {
      "name": "TheKlesticle",
      "rank": 692,
      "level_score": 14853
    },
    {
      "name": "Chaeng",
      "rank": 693,
      "level_score": 14851
    },
    {
      "name": "zwe",
      "rank": 694,
      "level_score": 14849
    },
    {
      "name": "Romam",
      "rank": 695,
      "level_score": 14846
    },
    {
      "name": "..",
      "rank": 696,
      "level_score": 14846
    },
    {
      "name": "brarikepta",
      "rank": 697,
      "level_score": 14844
    },
    {
      "name": "Pepper™",
      "rank": 698,
      "level_score": 14843
    },
    {
      "name": "19324611",
      "rank": 699,
      "level_score": 14841
    },
    {
      "name": "ВАГИНА ДЕЛЬФИНА",
      "rank": 700,
      "level_score": 14840
    },
    {
      "name": "Mage",
      "rank": 701,
      "level_score": 14835
    },
    {
      "name": "高端的队友总是以敌人",
      "rank": 702,
      "level_score": 14835
    },
    {
      "name": "Vĩnh Bình",
      "rank": 703,
      "level_score": 14835
    },
    {
      "name": "Hutgood",
      "rank": 704,
      "level_score": 14835
    },
    {
      "name": "danzail",
      "rank": 705,
      "level_score": 14833
    },
    {
      "name": "[DT] Lulu",
      "rank": 706,
      "level_score": 14831
    },
    {
      "name": "El Cabrón",
      "rank": 707,
      "level_score": 14828
    },
    {
      "name": "Краснодар",
      "rank": 708,
      "level_score": 14827
    },
    {
      "name": "実愛の左",
      "rank": 709,
      "level_score": 14825
    },
    {
      "name": "Gabriel[XO]",
      "rank": 710,
      "level_score": 14825
    },
    {
      "name": "drkylmaz",
      "rank": 711,
      "level_score": 14824
    },
    {
      "name": "Mars Volta",
      "rank": 712,
      "level_score": 14822
    },
    {
      "name": "Red eyE",
      "rank": 713,
      "level_score": 14819
    },
    {
      "name": "Jmunji",
      "rank": 714,
      "level_score": 14817
    },
    {
      "name": "Mramara",
      "rank": 715,
      "level_score": 14815
    },
    {
      "name": "anastaiiiiiiiiiiiii",
      "rank": 716,
      "level_score": 14813
    },
    {
      "name": "Gregory",
      "rank": 717,
      "level_score": 14812
    },
    {
      "name": "Raton Cafriles",
      "rank": 718,
      "level_score": 14807
    },
    {
      "name": "XtraLongChiliCheese",
      "rank": 719,
      "level_score": 14806
    },
    {
      "name": "tonyuk28",
      "rank": 720,
      "level_score": 14804
    },
    {
      "name": "Hari2BritNo8",
      "rank": 721,
      "level_score": 14803
    },
    {
      "name": "NEBRO",
      "rank": 722,
      "level_score": 14801
    },
    {
      "name": "ДИМОООН",
      "rank": 723,
      "level_score": 14800
    },
    {
      "name": "李寻 欢",
      "rank": 724,
      "level_score": 14798
    },
    {
      "name": "Lightness",
      "rank": 725,
      "level_score": 14795
    },
    {
      "name": "RΞVΞRIΞ",
      "rank": 726,
      "level_score": 14794
    },
    {
      "name": "Boom AoAe",
      "rank": 727,
      "level_score": 14792
    },
    {
      "name": "graboid",
      "rank": 728,
      "level_score": 14791
    },
    {
      "name": "zimbojones",
      "rank": 729,
      "level_score": 14790
    },
    {
      "name": "Soft drinks",
      "rank": 730,
      "level_score": 14787
    },
    {
      "name": "jiangbowen1984",
      "rank": 731,
      "level_score": 14785
    },
    {
      "name": "Galagher",
      "rank": 732,
      "level_score": 14785
    },
    {
      "name": "Rembo",
      "rank": 733,
      "level_score": 14783
    },
    {
      "name": "Red Hood.",
      "rank": 734,
      "level_score": 14782
    },
    {
      "name": "vp55521",
      "rank": 735,
      "level_score": 14782
    },
    {
      "name": "十个",
      "rank": 736,
      "level_score": 14776
    },
    {
      "name": "Vlashadka",
      "rank": 737,
      "level_score": 14774
    },
    {
      "name": "MangKULangiT",
      "rank": 738,
      "level_score": 14772
    },
    {
      "name": "player 1",
      "rank": 739,
      "level_score": 14771
    },
    {
      "name": "GoooDDDY",
      "rank": 740,
      "level_score": 14771
    },
    {
      "name": "The Curse",
      "rank": 741,
      "level_score": 14771
    },
    {
      "name": "Mr.Ali",
      "rank": 742,
      "level_score": 14769
    },
    {
      "name": "KevinYe",
      "rank": 743,
      "level_score": 14767
    },
    {
      "name": "V_FOX_V",
      "rank": 744,
      "level_score": 14765
    },
    {
      "name": "Raim04",
      "rank": 745,
      "level_score": 14763
    },
    {
      "name": "Hastle.rrror",
      "rank": 746,
      "level_score": 14761
    },
    {
      "name": "Cre4sy",
      "rank": 747,
      "level_score": 14761
    },
    {
      "name": "VLADIMIR PUTING",
      "rank": 748,
      "level_score": 14761
    },
    {
      "name": "地狱咆哮",
      "rank": 749,
      "level_score": 14759
    },
    {
      "name": "lucky28031990",
      "rank": 750,
      "level_score": 14759
    },
    {
      "name": "screamer",
      "rank": 751,
      "level_score": 14758
    },
    {
      "name": "Naofumi Iwatani",
      "rank": 752,
      "level_score": 14757
    },
    {
      "name": "ripple",
      "rank": 753,
      "level_score": 14751
    },
    {
      "name": "Serbitar",
      "rank": 754,
      "level_score": 14750
    },
    {
      "name": "muzj",
      "rank": 755,
      "level_score": 14748
    },
    {
      "name": ".",
      "rank": 756,
      "level_score": 14748
    },
    {
      "name": "filippo4ek12",
      "rank": 757,
      "level_score": 14748
    },
    {
      "name": "Mundraubritter",
      "rank": 758,
      "level_score": 14747
    },
    {
      "name": "z4ppy",
      "rank": 759,
      "level_score": 14745
    },
    {
      "name": "没问题！",
      "rank": 760,
      "level_score": 14743
    },
    {
      "name": "niklas.nilsson90",
      "rank": 761,
      "level_score": 14739
    },
    {
      "name": "as.4el",
      "rank": 762,
      "level_score": 14737
    },
    {
      "name": "Aramse",
      "rank": 763,
      "level_score": 14737
    },
    {
      "name": "Lickwid",
      "rank": 764,
      "level_score": 14737
    },
    {
      "name": "integer",
      "rank": 765,
      "level_score": 14736
    },
    {
      "name": "fl0ki",
      "rank": 766,
      "level_score": 14735
    },
    {
      "name": "Magnificent",
      "rank": 767,
      "level_score": 14730
    },
    {
      "name": "Tech-Noir",
      "rank": 768,
      "level_score": 14727
    },
    {
      "name": "NATI (>,'')>",
      "rank": 769,
      "level_score": 14723
    },
    {
      "name": "Олег",
      "rank": 770,
      "level_score": 14722
    },
    {
      "name": "qwender",
      "rank": 771,
      "level_score": 14720
    },
    {
      "name": "chilllintano",
      "rank": 772,
      "level_score": 14718
    },
    {
      "name": "ΠΑΣΟΚΑΡΑ",
      "rank": 773,
      "level_score": 14717
    },
    {
      "name": "Xinto",
      "rank": 774,
      "level_score": 14717
    },
    {
      "name": "Spartak",
      "rank": 775,
      "level_score": 14717
    },
    {
      "name": "Uvo",
      "rank": 776,
      "level_score": 14714
    },
    {
      "name": "johnsnavely",
      "rank": 777,
      "level_score": 14714
    },
    {
      "name": "Maurão",
      "rank": 778,
      "level_score": 14714
    },
    {
      "name": "Somboy",
      "rank": 779,
      "level_score": 14712
    },
    {
      "name": "Icycold",
      "rank": 780,
      "level_score": 14712
    },
    {
      "name": "cha0t1cz",
      "rank": 781,
      "level_score": 14711
    },
    {
      "name": "Tousan (all muted)",
      "rank": 782,
      "level_score": 14711
    },
    {
      "name": "osmosis",
      "rank": 783,
      "level_score": 14711
    },
    {
      "name": "It Ain't Me",
      "rank": 784,
      "level_score": 14709
    },
    {
      "name": "192",
      "rank": 785,
      "level_score": 14708
    },
    {
      "name": "neponzazaso",
      "rank": 786,
      "level_score": 14707
    },
    {
      "name": "全世界最可爱的人",
      "rank": 787,
      "level_score": 14707
    },
    {
      "name": "Rubber Duckiey",
      "rank": 788,
      "level_score": 14706
    },
    {
      "name": "JimmyJeeb",
      "rank": 789,
      "level_score": 14706
    },
    {
      "name": "DieGo!",
      "rank": 790,
      "level_score": 14704
    },
    {
      "name": "p$ux1@tro$",
      "rank": 791,
      "level_score": 14704
    },
    {
      "name": "Tyrion",
      "rank": 792,
      "level_score": 14704
    },
    {
      "name": "Doggo",
      "rank": 793,
      "level_score": 14699
    },
    {
      "name": "AndyWhiteLV",
      "rank": 794,
      "level_score": 14696
    },
    {
      "name": "equilibriummmm1",
      "rank": 795,
      "level_score": 14696
    },
    {
      "name": "lowEko",
      "rank": 796,
      "level_score": 14695
    },
    {
      "name": "床前明月光",
      "rank": 797,
      "level_score": 14694
    },
    {
      "name": "pepa",
      "rank": 798,
      "level_score": 14693
    },
    {
      "name": "Uki",
      "rank": 799,
      "level_score": 14692
    },
    {
      "name": "tox",
      "rank": 800,
      "level_score": 14690
    },
    {
      "name": "Beer_Drinker",
      "rank": 801,
      "level_score": 14690
    },
    {
      "name": "Tench",
      "rank": 802,
      "level_score": 14683
    },
    {
      "name": "Klaad",
      "rank": 803,
      "level_score": 14674
    },
    {
      "name": "mr.angelgod",
      "rank": 804,
      "level_score": 14674
    },
    {
      "name": "Yeezus",
      "rank": 805,
      "level_score": 14673
    },
    {
      "name": "eatinapineapple",
      "rank": 806,
      "level_score": 14672
    },
    {
      "name": "Lasmala",
      "rank": 807,
      "level_score": 14671
    },
    {
      "name": "Bam",
      "rank": 808,
      "level_score": 14661
    },
    {
      "name": "GsP ᶠᶸᶜᵏᵧₒᵤ",
      "rank": 809,
      "level_score": 14661
    },
    {
      "name": "NOTHING",
      "rank": 810,
      "level_score": 14660
    },
    {
      "name": "jayatsena",
      "rank": 811,
      "level_score": 14659
    },
    {
      "name": "Golgothane",
      "rank": 812,
      "level_score": 14659
    },
    {
      "name": "Good Ju Ju",
      "rank": 813,
      "level_score": 14659
    },
    {
      "name": "godlowyang",
      "rank": 814,
      "level_score": 14657
    },
    {
      "name": "AzuLeJo",
      "rank": 815,
      "level_score": 14654
    },
    {
      "name": "BamiGun",
      "rank": 816,
      "level_score": 14653
    },
    {
      "name": "членпипен",
      "rank": 817,
      "level_score": 14652
    },
    {
      "name": "ПЕНЕТРАТОР 3000",
      "rank": 818,
      "level_score": 14646
    },
    {
      "name": "ZeeBeeKak",
      "rank": 819,
      "level_score": 14644
    },
    {
      "name": "SekoTX",
      "rank": 820,
      "level_score": 14643
    },
    {
      "name": "461107825",
      "rank": 821,
      "level_score": 14643
    },
    {
      "name": "Private Bank-King",
      "rank": 822,
      "level_score": 14643
    },
    {
      "name": "Ecstasy",
      "rank": 823,
      "level_score": 14641
    },
    {
      "name": "zazoby",
      "rank": 824,
      "level_score": 14641
    },
    {
      "name": "3154",
      "rank": 825,
      "level_score": 14637
    },
    {
      "name": "EMI",
      "rank": 826,
      "level_score": 14636
    },
    {
      "name": "////////////////////////////////",
      "rank": 827,
      "level_score": 14635
    },
    {
      "name": "Jeppz",
      "rank": 828,
      "level_score": 14632
    },
    {
      "name": "热刺三连败",
      "rank": 829,
      "level_score": 14627
    },
    {
      "name": "Pikabyla",
      "rank": 830,
      "level_score": 14627
    },
    {
      "name": "Yêu Bé Huyền",
      "rank": 831,
      "level_score": 14626
    },
    {
      "name": "SahTar",
      "rank": 832,
      "level_score": 14626
    },
    {
      "name": "oxxxymirana",
      "rank": 833,
      "level_score": 14625
    },
    {
      "name": "s2",
      "rank": 834,
      "level_score": 14624
    },
    {
      "name": "Dact4",
      "rank": 835,
      "level_score": 14624
    },
    {
      "name": "IchiPunani",
      "rank": 836,
      "level_score": 14623
    },
    {
      "name": "hean厉害",
      "rank": 837,
      "level_score": 14622
    },
    {
      "name": "Loveboat",
      "rank": 838,
      "level_score": 14620
    },
    {
      "name": "Tony Ma",
      "rank": 839,
      "level_score": 14619
    },
    {
      "name": "greatoldone",
      "rank": 840,
      "level_score": 14618
    },
    {
      "name": "KAkZaMan",
      "rank": 841,
      "level_score": 14617
    },
    {
      "name": "BanQuo",
      "rank": 842,
      "level_score": 14612
    },
    {
      "name": "Stop it",
      "rank": 843,
      "level_score": 14609
    },
    {
      "name": "Shadow666",
      "rank": 844,
      "level_score": 14608
    },
    {
      "name": "mez",
      "rank": 845,
      "level_score": 14607
    },
    {
      "name": "NickQ",
      "rank": 846,
      "level_score": 14605
    },
    {
      "name": "nik",
      "rank": 847,
      "level_score": 14605
    },
    {
      "name": "Beutelgeuse",
      "rank": 848,
      "level_score": 14605
    },
    {
      "name": "Stuck at archons",
      "rank": 849,
      "level_score": 14604
    },
    {
      "name": "saymon88",
      "rank": 850,
      "level_score": 14604
    },
    {
      "name": "The_OriginaI",
      "rank": 851,
      "level_score": 14601
    },
    {
      "name": "vadosikkozlov",
      "rank": 852,
      "level_score": 14600
    },
    {
      "name": "Dad",
      "rank": 853,
      "level_score": 14596
    },
    {
      "name": "Mitzy sama",
      "rank": 854,
      "level_score": 14595
    },
    {
      "name": "linzzzz",
      "rank": 855,
      "level_score": 14594
    },
    {
      "name": "coe",
      "rank": 856,
      "level_score": 14593
    },
    {
      "name": "b1010",
      "rank": 857,
      "level_score": 14591
    },
    {
      "name": "Giles",
      "rank": 858,
      "level_score": 14591
    },
    {
      "name": "夜之陨",
      "rank": 859,
      "level_score": 14588
    },
    {
      "name": "Zighi",
      "rank": 860,
      "level_score": 14588
    },
    {
      "name": "EXC[I]SE",
      "rank": 861,
      "level_score": 14587
    },
    {
      "name": "china8250",
      "rank": 862,
      "level_score": 14583
    },
    {
      "name": "BourkeStreet",
      "rank": 863,
      "level_score": 14583
    },
    {
      "name": "Piston",
      "rank": 864,
      "level_score": 14575
    },
    {
      "name": "RoAsTeD",
      "rank": 865,
      "level_score": 14575
    },
    {
      "name": "老人要用脑子打",
      "rank": 866,
      "level_score": 14572
    },
    {
      "name": "WANCHALERM AFK",
      "rank": 867,
      "level_score": 14571
    },
    {
      "name": "ChakeGSOM",
      "rank": 868,
      "level_score": 14570
    },
    {
      "name": "KorekGass",
      "rank": 869,
      "level_score": 14569
    },
    {
      "name": "Sured",
      "rank": 870,
      "level_score": 14568
    },
    {
      "name": "asffare",
      "rank": 871,
      "level_score": 14568
    },
    {
      "name": "saloufa GR",
      "rank": 872,
      "level_score": 14568
    },
    {
      "name": "fbz",
      "rank": 873,
      "level_score": 14567
    },
    {
      "name": "76561198125664397",
      "rank": 874,
      "level_score": 14565
    },
    {
      "name": "Ken Mindaz",
      "rank": 875,
      "level_score": 14565
    },
    {
      "name": "KlasseKlaus",
      "rank": 876,
      "level_score": 14564
    },
    {
      "name": "Skogstad",
      "rank": 877,
      "level_score": 14563
    },
    {
      "name": "Consoul",
      "rank": 878,
      "level_score": 14557
    },
    {
      "name": "o.tchulckov",
      "rank": 879,
      "level_score": 14557
    },
    {
      "name": "Apm43",
      "rank": 880,
      "level_score": 14557
    },
    {
      "name": "西德最新科技",
      "rank": 881,
      "level_score": 14556
    },
    {
      "name": "changlitutechandaigou",
      "rank": 882,
      "level_score": 14554
    },
    {
      "name": "=S.T.A.R.= Cheeseburger",
      "rank": 883,
      "level_score": 14554
    },
    {
      "name": "xandr",
      "rank": 884,
      "level_score": 14552
    },
    {
      "name": "Harlon",
      "rank": 885,
      "level_score": 14548
    },
    {
      "name": "ROCKnROLL",
      "rank": 886,
      "level_score": 14548
    },
    {
      "name": "ティー",
      "rank": 887,
      "level_score": 14545
    },
    {
      "name": "马什么梅-.-",
      "rank": 888,
      "level_score": 14545
    },
    {
      "name": "小鸟哔哔",
      "rank": 889,
      "level_score": 14541
    },
    {
      "name": "WinterIsGoing",
      "rank": 890,
      "level_score": 14536
    },
    {
      "name": "DUngDattenVOVan",
      "rank": 891,
      "level_score": 14535
    },
    {
      "name": "Mute",
      "rank": 892,
      "level_score": 14533
    },
    {
      "name": "Striker",
      "rank": 893,
      "level_score": 14530
    },
    {
      "name": "Carpenterwang",
      "rank": 894,
      "level_score": 14527
    },
    {
      "name": "₭ɄJł",
      "rank": 895,
      "level_score": 14526
    },
    {
      "name": "Swagdaddy71 (narcobaby)",
      "rank": 896,
      "level_score": 14526
    },
    {
      "name": "Minn Ko Yee",
      "rank": 897,
      "level_score": 14525
    },
    {
      "name": "SHA-Doc",
      "rank": 898,
      "level_score": 14525
    },
    {
      "name": "gsr",
      "rank": 899,
      "level_score": 14524
    },
    {
      "name": "moneg",
      "rank": 900,
      "level_score": 14523
    },
    {
      "name": "kbl",
      "rank": 901,
      "level_score": 14522
    },
    {
      "name": "Bezdna",
      "rank": 902,
      "level_score": 14518
    },
    {
      "name": "Vandam",
      "rank": 903,
      "level_score": 14515
    },
    {
      "name": "PECO",
      "rank": 904,
      "level_score": 14502
    },
    {
      "name": "tonsilog",
      "rank": 905,
      "level_score": 14501
    },
    {
      "name": "Somsri422r",
      "rank": 906,
      "level_score": 14495
    },
    {
      "name": "театр бикало!",
      "rank": 907,
      "level_score": 14494
    },
    {
      "name": "Su1tca5e Full 0f Sh4RtS",
      "rank": 908,
      "level_score": 14489
    },
    {
      "name": "愤世嫉俗的午夜计划",
      "rank": 909,
      "level_score": 14485
    },
    {
      "name": "Achtung!(Ukraine)",
      "rank": 910,
      "level_score": 14483
    },
    {
      "name": "37",
      "rank": 911,
      "level_score": 14476
    },
    {
      "name": "Visvim",
      "rank": 912,
      "level_score": 14476
    },
    {
      "name": "Chandler Muriel Bing",
      "rank": 913,
      "level_score": 14474
    },
    {
      "name": "than7than",
      "rank": 914,
      "level_score": 14472
    },
    {
      "name": "CrunchyPeanut_Butter",
      "rank": 915,
      "level_score": 14470
    },
    {
      "name": "aldwinligaya",
      "rank": 916,
      "level_score": 14467
    },
    {
      "name": "SGT BURNESHOT",
      "rank": 917,
      "level_score": 14464
    },
    {
      "name": "Aesukrist",
      "rank": 918,
      "level_score": 14459
    },
    {
      "name": "Dr._Zl0",
      "rank": 919,
      "level_score": 14456
    },
    {
      "name": "abirvalg94",
      "rank": 920,
      "level_score": 14454
    },
    {
      "name": "batmand",
      "rank": 921,
      "level_score": 14448
    },
    {
      "name": "KOT",
      "rank": 922,
      "level_score": 14445
    },
    {
      "name": "падла",
      "rank": 923,
      "level_score": 14444
    },
    {
      "name": "Daegon",
      "rank": 924,
      "level_score": 14436
    },
    {
      "name": "Saul Goodman",
      "rank": 925,
      "level_score": 14428
    },
    {
      "name": "Monster",
      "rank": 926,
      "level_score": 14428
    },
    {
      "name": "utongakbar8285",
      "rank": 927,
      "level_score": 14423
    },
    {
      "name": "OG-Goku",
      "rank": 928,
      "level_score": 14419
    },
    {
      "name": "Neuritis",
      "rank": 929,
      "level_score": 14417
    },
    {
      "name": "TTv.StikkoManiac",
      "rank": 930,
      "level_score": 14414
    },
    {
      "name": "John",
      "rank": 931,
      "level_score": 14413
    },
    {
      "name": "Give me ZHU",
      "rank": 932,
      "level_score": 14412
    },
    {
      "name": "Nikita12",
      "rank": 933,
      "level_score": 14408
    },
    {
      "name": "520goddess",
      "rank": 934,
      "level_score": 14406
    },
    {
      "name": "mmishinb",
      "rank": 935,
      "level_score": 14406
    },
    {
      "name": "BumBumPawn",
      "rank": 936,
      "level_score": 14405
    },
    {
      "name": "db",
      "rank": 937,
      "level_score": 14404
    },
    {
      "name": "Твори добро",
      "rank": 938,
      "level_score": 14404
    },
    {
      "name": "Chewsday",
      "rank": 939,
      "level_score": 14399
    },
    {
      "name": ".",
      "rank": 940,
      "level_score": 14394
    },
    {
      "name": "lapkohookah",
      "rank": 941,
      "level_score": 14392
    },
    {
      "name": "Né Em Ra",
      "rank": 942,
      "level_score": 14388
    },
    {
      "name": "MeetSomlab",
      "rank": 943,
      "level_score": 14384
    },
    {
      "name": "Сайф",
      "rank": 944,
      "level_score": 14379
    },
    {
      "name": "淡黄的长裙，蓬松的头",
      "rank": 945,
      "level_score": 14377
    },
    {
      "name": "Antz",
      "rank": 946,
      "level_score": 14371
    },
    {
      "name": "yfpfh11",
      "rank": 947,
      "level_score": 14369
    },
    {
      "name": "-TochiS-",
      "rank": 948,
      "level_score": 14363
    },
    {
      "name": "Bim",
      "rank": 949,
      "level_score": 14361
    },
    {
      "name": "tkj399",
      "rank": 950,
      "level_score": 14358
    },
    {
      "name": "ChicoBestia",
      "rank": 951,
      "level_score": 14357
    },
    {
      "name": "DOGE",
      "rank": 952,
      "level_score": 14356
    },
    {
      "name": "Ambyarr",
      "rank": 953,
      "level_score": 14353
    },
    {
      "name": "Z",
      "rank": 954,
      "level_score": 14351
    },
    {
      "name": "void",
      "rank": 955,
      "level_score": 14348
    },
    {
      "name": "mims",
      "rank": 956,
      "level_score": 14346
    },
    {
      "name": "nugrahaga",
      "rank": 957,
      "level_score": 14341
    },
    {
      "name": "Time To-Hate",
      "rank": 958,
      "level_score": 14341
    },
    {
      "name": "[B]east[P]riest",
      "rank": 959,
      "level_score": 14336
    },
    {
      "name": "Янне",
      "rank": 960,
      "level_score": 14332
    },
    {
      "name": "Hansel",
      "rank": 961,
      "level_score": 14327
    },
    {
      "name": "oooooo",
      "rank": 962,
      "level_score": 14324
    },
    {
      "name": "observer",
      "rank": 963,
      "level_score": 14320
    },
    {
      "name": "NN",
      "rank": 964,
      "level_score": 14316
    },
    {
      "name": "RonskiKnight",
      "rank": 965,
      "level_score": 14315
    },
    {
      "name": "Seveem",
      "rank": 966,
      "level_score": 14309
    },
    {
      "name": "buzheng",
      "rank": 967,
      "level_score": 14306
    },
    {
      "name": "壹只耳",
      "rank": 968,
      "level_score": 14306
    },
    {
      "name": "STRANNik",
      "rank": 969,
      "level_score": 14305
    },
    {
      "name": "†y †aker",
      "rank": 970,
      "level_score": 14305
    },
    {
      "name": "mishaaaa",
      "rank": 971,
      "level_score": 14304
    },
    {
      "name": "14882453",
      "rank": 972,
      "level_score": 14304
    },
    {
      "name": "aPsu",
      "rank": 973,
      "level_score": 14291
    },
    {
      "name": "765611982118456**",
      "rank": 974,
      "level_score": 14291
    },
    {
      "name": "KOZAK DMYTRO",
      "rank": 975,
      "level_score": 14290
    },
    {
      "name": "V3nomouss",
      "rank": 976,
      "level_score": 14287
    },
    {
      "name": "Bittah Demon",
      "rank": 977,
      "level_score": 14280
    },
    {
      "name": "D_m_itriy",
      "rank": 978,
      "level_score": 14275
    },
    {
      "name": "WickedJimbo",
      "rank": 979,
      "level_score": 14272
    },
    {
      "name": "heyyo",
      "rank": 980,
      "level_score": 14269
    },
    {
      "name": "tofinn",
      "rank": 981,
      "level_score": 14259
    },
    {
      "name": "Whatever",
      "rank": 982,
      "level_score": 14258
    },
    {
      "name": "dngr-_-",
      "rank": 983,
      "level_score": 14256
    },
    {
      "name": "sharki",
      "rank": 984,
      "level_score": 14245
    },
    {
      "name": "Zeta",
      "rank": 985,
      "level_score": 14240
    },
    {
      "name": "ao? giac' ma`",
      "rank": 986,
      "level_score": 14234
    },
    {
      "name": "haseoplex",
      "rank": 987,
      "level_score": 14232
    },
    {
      "name": "Gizmo",
      "rank": 988,
      "level_score": 14218
    },
    {
      "name": "kenavr",
      "rank": 989,
      "level_score": 14218
    },
    {
      "name": "蘑菇灬袋鼠彡",
      "rank": 990,
      "level_score": 14218
    },
    {
      "name": "deltaT",
      "rank": 991,
      "level_score": 14211
    },
    {
      "name": "Ryzar",
      "rank": 992,
      "level_score": 14211
    },
    {
      "name": "GAGIK PUTAMADREZ",
      "rank": 993,
      "level_score": 14206
    },
    {
      "name": "jmccabe18",
      "rank": 994,
      "level_score": 14205
    },
    {
      "name": "raDУЙся",
      "rank": 995,
      "level_score": 14202
    },
    {
      "name": "emoer1988",
      "rank": 996,
      "level_score": 14200
    },
    {
      "name": "timedidi",
      "rank": 997,
      "level_score": 14199
    },
    {
      "name": "MajorJuggler",
      "rank": 998,
      "level_score": 14193
    },
    {
      "name": "CheDeeSIV",
      "rank": 999,
      "level_score": 14191
    },
    {
      "name": "portugalmirandaregina",
      "rank": 1000,
      "level_score": 14186
    },
    {
      "name": "пожилой капитан",
      "rank": 1001,
      "level_score": 14174
    },
    {
      "name": "MrSnoops",
      "rank": 1002,
      "level_score": 14174
    },
    {
      "name": "Nguyễn Trãi",
      "rank": 1003,
      "level_score": 14171
    },
    {
      "name": "top_gun",
      "rank": 1004,
      "level_score": 14171
    },
    {
      "name": "钟声",
      "rank": 1005,
      "level_score": 14160
    },
    {
      "name": "Hippie Johnny",
      "rank": 1006,
      "level_score": 14158
    },
    {
      "name": "Miny",
      "rank": 1007,
      "level_score": 14148
    },
    {
      "name": "Monstilus",
      "rank": 1008,
      "level_score": 14145
    },
    {
      "name": "DeadMemories7",
      "rank": 1009,
      "level_score": 14138
    },
    {
      "name": "shipr",
      "rank": 1010,
      "level_score": 14136
    },
    {
      "name": "iPuzza",
      "rank": 1011,
      "level_score": 14134
    },
    {
      "name": "JiHAD",
      "rank": 1012,
      "level_score": 14128
    },
    {
      "name": "Kos",
      "rank": 1013,
      "level_score": 14126
    },
    {
      "name": "框框",
      "rank": 1014,
      "level_score": 14118
    },
    {
      "name": "Cak3",
      "rank": 1015,
      "level_score": 14096
    },
    {
      "name": "Gang3r",
      "rank": 1016,
      "level_score": 14079
    },
    {
      "name": "Solear",
      "rank": 1017,
      "level_score": 14074
    },
    {
      "name": "Мирный житель",
      "rank": 1018,
      "level_score": 14073
    },
    {
      "name": "Генрих",
      "rank": 1019,
      "level_score": 14063
    },
    {
      "name": "TOTIK",
      "rank": 1020,
      "level_score": 14056
    },
    {
      "name": "BARUN",
      "rank": 1021,
      "level_score": 14054
    },
    {
      "name": "CreamPuff",
      "rank": 1022,
      "level_score": 14048
    },
    {
      "name": "Подкованный",
      "rank": 1023,
      "level_score": 14046
    },
    {
      "name": "Az",
      "rank": 1024,
      "level_score": 14038
    },
    {
      "name": "schmitzdorf",
      "rank": 1025,
      "level_score": 14025
    },
    {
      "name": "WentFox'",
      "rank": 1026,
      "level_score": 14011
    },
    {
      "name": "mr_Ibriev",
      "rank": 1027,
      "level_score": 13985
    },
    {
      "name": "Simple",
      "rank": 1028,
      "level_score": 13984
    },
    {
      "name": "xumin1027",
      "rank": 1029,
      "level_score": 13970
    },
    {
      "name": "TIMO",
      "rank": 1030,
      "level_score": 13970
    },
    {
      "name": "kL1n",
      "rank": 1031,
      "level_score": 13962
    },
    {
      "name": "JWakari",
      "rank": 1032,
      "level_score": 13962
    },
    {
      "name": "Tùng Tả",
      "rank": 1033,
      "level_score": 13960
    },
    {
      "name": "Inkvizitor",
      "rank": 1034,
      "level_score": 13951
    },
    {
      "name": "merci12995",
      "rank": 1035,
      "level_score": 13944
    },
    {
      "name": "johnwoo",
      "rank": 1036,
      "level_score": 13939
    },
    {
      "name": "KellyWangWZ",
      "rank": 1037,
      "level_score": 13938
    },
    {
      "name": "Потянул ПАХ",
      "rank": 1038,
      "level_score": 13937
    },
    {
      "name": "Hipster Crocodile",
      "rank": 1039,
      "level_score": 13888
    },
    {
      "name": "Lucker",
      "rank": 1040,
      "level_score": 13843
    },
    {
      "name": "没开声音，有事打字",
      "rank": 1041,
      "level_score": 13832
    },
    {
      "name": "Lop",
      "rank": 1042,
      "level_score": 13809
    },
    {
      "name": "Vovan",
      "rank": 1043,
      "level_score": 13798
    },
    {
      "name": "hookslide4",
      "rank": 1044,
      "level_score": 13787
    },
    {
      "name": "Dimania",
      "rank": 1045,
      "level_score": 13783
    },
    {
      "name": "All my pay in alcohol & drugs",
      "rank": 1046,
      "level_score": 13744
    },
    {
      "name": "warlock",
      "rank": 1047,
      "level_score": 13730
    },
    {
      "name": "BenWill",
      "rank": 1048,
      "level_score": 13722
    },
    {
      "name": "MARKIE",
      "rank": 1049,
      "level_score": 13673
    },
    {
      "name": "Uter_buter",
      "rank": 1050,
      "level_score": 13595
    },
    {
      "name": "PASHQWE",
      "rank": 1051,
      "level_score": 13445
    },
    {
      "name": "Badfinger",
      "rank": 1052,
      "level_score": 13367
    },
    {
      "name": "Mc_Zigg_Zagg_tv",
      "rank": 1053,
      "level_score": 13178
    },
    {
      "name": "214627726",
      "rank": 1054,
      "level_score": 13120
    },
    {
      "name": "pep",
      "rank": 1055,
      "level_score": 13000
    }
  ],
  "success": true
}
